aiochainscan/__init__.py
aiochainscan/aiochainscan_fastabi.pyi
aiochainscan/capabilities.py
aiochainscan/chain_registry.py
aiochainscan/cli.py
aiochainscan/client.py
aiochainscan/common.py
aiochainscan/config.py
aiochainscan/decode.py
aiochainscan/exceptions.py
aiochainscan/network.py
aiochainscan/py.typed
aiochainscan/url_builder.py
aiochainscan/adapters/__init__.py
aiochainscan/adapters/aiohttp_client.py
aiochainscan/adapters/aiohttp_graphql_client.py
aiochainscan/adapters/blockscout_graphql_builder.py
aiochainscan/adapters/endpoint_builder_urlbuilder.py
aiochainscan/adapters/memory_cache.py
aiochainscan/adapters/noop_telemetry.py
aiochainscan/adapters/retry_exponential.py
aiochainscan/adapters/simple_provider_federator.py
aiochainscan/adapters/simple_rate_limiter.py
aiochainscan/adapters/structlog_telemetry.py
aiochainscan/core/__init__.py
aiochainscan/core/client.py
aiochainscan/core/endpoint.py
aiochainscan/core/method.py
aiochainscan/domain/__init__.py
aiochainscan/domain/dto.py
aiochainscan/domain/models.py
aiochainscan/fastabi/Cargo.lock
aiochainscan/fastabi/Cargo.toml
aiochainscan/fastabi/src/lib.rs
aiochainscan/modules/account.py
aiochainscan/modules/base.py
aiochainscan/modules/block.py
aiochainscan/modules/contract.py
aiochainscan/modules/gas_tracker.py
aiochainscan/modules/logs.py
aiochainscan/modules/proxy.py
aiochainscan/modules/stats.py
aiochainscan/modules/token.py
aiochainscan/modules/transaction.py
aiochainscan/modules/extra/links.py
aiochainscan/modules/extra/utils.py
aiochainscan/ports/__init__.py
aiochainscan/ports/cache.py
aiochainscan/ports/endpoint_builder.py
aiochainscan/ports/graphql_client.py
aiochainscan/ports/graphql_query_builder.py
aiochainscan/ports/http_client.py
aiochainscan/ports/provider_federator.py
aiochainscan/ports/rate_limiter.py
aiochainscan/ports/telemetry.py
aiochainscan/scanners/__init__.py
aiochainscan/scanners/_etherscan_like.py
aiochainscan/scanners/base.py
aiochainscan/scanners/blockscout_v1.py
aiochainscan-0.2.3.dist-info/METADATA
aiochainscan-0.2.3.dist-info/WHEEL
aiochainscan-0.2.3.dist-info/entry_points.txt
aiochainscan-0.2.3.dist-info/top_level.txt
aiochainscan-0.2.3.dist-info/RECORD
