Metadata-Version: 2.4
Name: aiochainscan
Version: 0.2.3
Summary: Chainscan API async Python wrapper
Author-email: VaitaR <andrey.shivalin@gmail.com>
License: MIT
Project-URL: Homepage, https://github.com/VaitaR/aiochainscan
Project-URL: Repository, https://github.com/VaitaR/aiochainscan
Project-URL: Issues, https://github.com/VaitaR/aiochainscan/issues
Classifier: Development Status :: 4 - Beta
Classifier: Intended Audience :: Developers
Classifier: License :: OSI Approved :: MIT License
Classifier: Programming Language :: Python :: 3
Classifier: Programming Language :: Python :: 3.10
Classifier: Programming Language :: Python :: 3.11
Classifier: Programming Language :: Python :: 3.12
Requires-Python: >=3.10
Requires-Dist: aiohttp>=3.4
Requires-Dist: asyncio-throttle>=1.0.1
Requires-Dist: aiohttp-retry>=2.8.3
Requires-Dist: pycryptodome
Requires-Dist: eth-abi
Requires-Dist: requests>=2.31.0
Requires-Dist: structlog>=23.1.0
Provides-Extra: dev
Requires-Dist: pytest>=7.1.2; extra == "dev"
Requires-Dist: pytest-asyncio>=0.21.1; extra == "dev"
Requires-Dist: pytest-cov>=4.0.0; extra == "dev"
Requires-Dist: pytest-benchmark>=4.0.0; extra == "dev"
Requires-Dist: pre-commit>=3.5.0; extra == "dev"
Requires-Dist: coveralls>=3.3.1; extra == "dev"
Requires-Dist: ruff==0.4.7; extra == "dev"
Requires-Dist: mypy; extra == "dev"
Requires-Dist: import-linter>=2.0.0; extra == "dev"
Provides-Extra: fast
Requires-Dist: maturin<2.0,>=1.6; extra == "fast"
